app/__init__.py
app/__main__.py
app/dependencies.py
app/main.py
app/models.py
app/cli/__init__.py
app/cli/constants.py
app/cli/helpers.py
app/cli/main.py
app/cli/stdio.py
app/cli/helm/__init__.py
app/cli/helm/constants.py
app/cli/helm/helpers.py
app/cli/helm/main.py
app/cli/helm/cli/__init__.py
app/cli/helm/cli/helm.py
app/cli/helm/cli/kubectl.py
app/cli/helm/cli/py.typed
app/common/__init__.py
app/common/constants.py
app/common/getenv.py
app/common/logger.py
app/common/shutil.py
app/core/__init__.py
app/core/fastapi_mcp.py
app/core/py.typed
app/core/settings.py
app/routers/__init__.py
app/routers/selenium_proxy.py
app/routers/browsers/__init__.py
app/routers/browsers/models.py
app/routers/browsers/routes.py
app/services/__init__.py
app/services/metrics.py
app/services/selenium_hub/__init__.py
app/services/selenium_hub/_selenium_hub.py
app/services/selenium_hub/manager.py
app/services/selenium_hub/py.typed
app/services/selenium_hub/common/__init__.py
app/services/selenium_hub/common/logger.py
app/services/selenium_hub/common/pidfile.py
app/services/selenium_hub/core/__init__.py
app/services/selenium_hub/core/docker_backend.py
app/services/selenium_hub/core/hub_backend.py
app/services/selenium_hub/core/kubernetes/__init__.py
app/services/selenium_hub/core/kubernetes/backend.py
app/services/selenium_hub/core/kubernetes/k8s_config.py
app/services/selenium_hub/core/kubernetes/k8s_models.py
app/services/selenium_hub/core/kubernetes/k8s_port_forwarder.py
app/services/selenium_hub/core/kubernetes/k8s_resource_manager.py
app/services/selenium_hub/core/kubernetes/k8s_url_resolver.py
app/services/selenium_hub/core/kubernetes/common/__init__.py
app/services/selenium_hub/core/kubernetes/common/auth.py
app/services/selenium_hub/core/kubernetes/common/constants.py
app/services/selenium_hub/core/kubernetes/common/decorators.py
app/services/selenium_hub/models/__init__.py
app/services/selenium_hub/models/browser.py
app/services/selenium_hub/models/docker_settings.py
mcp_selenium_grid-0.1.0.dev8.dist-info/METADATA
mcp_selenium_grid-0.1.0.dev8.dist-info/WHEEL
mcp_selenium_grid-0.1.0.dev8.dist-info/entry_points.txt
mcp_selenium_grid-0.1.0.dev8.dist-info/licenses/LICENSE
mcp_selenium_grid-0.1.0.dev8.dist-info/RECORD
