Metadata-Version: 2.4
Name: mcp-selenium-grid
Version: 0.1.0.dev8
Summary: MCP Server for managing Selenium Grid
Author: falamarcao <https://github.com/falamarcao>, CatchNip <https://github.com/CatchNip>
License: MIT License
License-File: LICENSE
Classifier: Framework :: FastAPI
Classifier: Framework :: Pydantic
Classifier: Intended Audience :: Developers
Classifier: Intended Audience :: Information Technology
Classifier: License :: OSI Approved :: MIT License
Classifier: Operating System :: OS Independent
Classifier: Programming Language :: Python :: 3
Classifier: Programming Language :: Python :: 3.12
Classifier: Programming Language :: Python :: 3.13
Classifier: Topic :: Internet :: WWW/HTTP :: Browsers
Classifier: Topic :: Scientific/Engineering :: Artificial Intelligence
Classifier: Topic :: Software Development
Classifier: Topic :: Software Development :: Testing
Classifier: Typing :: Typed
Requires-Python: >=3.12
Requires-Dist: anyio>=4.10.0
Requires-Dist: asgi-lifespan>=2.1.0
Requires-Dist: docker>=7.1.0
Requires-Dist: fastapi-cli[standard-no-fastapi-cloud-cli]>=0.0.11
Requires-Dist: fastapi-mcp>=0.4.0
Requires-Dist: fastapi[standard]>=0.116.1
Requires-Dist: fastmcp[stdio]>=2.12.2
Requires-Dist: httpx>=0.28.1
Requires-Dist: kubernetes>=33.1.0
Requires-Dist: prometheus-client>=0.22.1
Requires-Dist: prometheus-fastapi-instrumentator>=7.1.0
Requires-Dist: psutil>=7.0.0
Requires-Dist: pydantic-settings>=2.10.1
Requires-Dist: pydantic>=2.11.7
Requires-Dist: typer>=0.17.4
Requires-Dist: uvicorn>=0.35.0
Provides-Extra: test
Requires-Dist: coverage>=7.10.6; extra == 'test'
Requires-Dist: pytest-asyncio>=1.1.0; extra == 'test'
Requires-Dist: pytest-mock>=3.15.0; extra == 'test'
Requires-Dist: pytest-sugar>=1.1.1; extra == 'test'
Requires-Dist: pytest-timeout>=2.4.0; extra == 'test'
Requires-Dist: pytest>=8.4.2; extra == 'test'
